<?xml version="1.0" encoding="UTF-8"?><record_update table="sys_atf_step">
    <sys_atf_step action="DELETE">
        <active>true</active>
        <callable_outputs/>
        <copied_from/>
        <description>Assert the following:
The following fields are visible: Backout plan, Watch list, Type, Conflict status, Communication Plan, Number, Test plan, CAB delegate, State, Configuration item, Impact, Define Security Impact, Work notes list, Service, Priority, Model, CAB recommendation, Requested by, Actual end date, Work notes, Implementation plan, Planned end date, Short description, Actual start date, Close code, Assignment group, Additional assignee list, Define Proposed Change, Service offering, Close notes, CAB required, Business Justification, Assigned to, Planned start date, Additional comments, Conflict last run, CAB date/time, Risk, Category, Compliance Impact, Operational Impact
The following fields are read only: Type, Conflict status, Number, Conflict last run
The following fields are mandatory: Define Proposed Change, Business Justification, Requested by, Short description
With a failure timeout of 30 Seconds</description>
        <display_name>Field State Validation</display_name>
        <inputs/>
        <mugshots_cache_json/>
        <notes/>
        <order>15</order>
        <step_config display_value="Field State Validation">1dfece935332120028bc29cac2dc3478</step_config>
        <sys_class_name>sys_atf_step</sys_class_name>
        <sys_created_by>admin</sys_created_by>
        <sys_created_on>2026-02-20 08:24:46</sys_created_on>
        <sys_id>bdc1132f87073e10375662060cbb3503</sys_id>
        <sys_mod_count>58</sys_mod_count>
        <sys_name>Field State Validation</sys_name>
        <sys_package display_value="Updater" source="x_g_s7s_updater">67d384af87c7b610375662060cbb35be</sys_package>
        <sys_policy/>
        <sys_scope display_value="Updater">67d384af87c7b610375662060cbb35be</sys_scope>
        <sys_update_name>sys_atf_step_bdc1132f87073e10375662060cbb3503</sys_update_name>
        <sys_updated_by>admin</sys_updated_by>
        <sys_updated_on>2026-02-20 15:23:33</sys_updated_on>
        <table>change_request</table>
        <test display_value="ATF Generated Test - change_request, Jay Simcox, User's default view (Default view)">a0c15feb87073e10375662060cbb357b</test>
        <timeout>1970-01-01 00:00:30</timeout>
        <warning_message/>
    </sys_atf_step>
    <sys_variable_value action="DELETE" query="document_key=bdc1132f87073e10375662060cbb3503"/>
    <sys_variable_value action="DELETE">
        <document>sys_atf_step</document>
        <document_key>bdc1132f87073e10375662060cbb3503</document_key>
        <order>200</order>
        <sys_class_name>sys_variable_value</sys_class_name>
        <sys_created_by>admin</sys_created_by>
        <sys_created_on>2026-02-20 08:24:46</sys_created_on>
        <sys_id>b5c1132f87073e10375662060cbb3505</sys_id>
        <sys_mod_count>0</sys_mod_count>
        <sys_updated_by>admin</sys_updated_by>
        <sys_updated_on>2026-02-20 08:24:46</sys_updated_on>
        <value>backout_plan,watch_list,type,conflict_status,u_communication_plan,number,test_plan,cab_delegate,state,cmdb_ci,impact,u_define_security_impact,work_notes_list,business_service,priority,chg_model,cab_recommendation,requested_by,work_end,work_notes,implementation_plan,end_date,short_description,work_start,close_code,assignment_group,additional_assignee_list,description,service_offering,close_notes,cab_required,justification,assigned_to,start_date,comments,conflict_last_run,cab_date_time,risk,category,u_compliance_impact,risk_impact_analysis</value>
        <variable display_value="Visible">0cd9df135320220002c6435723dc3426</variable>
    </sys_variable_value>
    <sys_variable_value action="DELETE">
        <document>sys_atf_step</document>
        <document_key>bdc1132f87073e10375662060cbb3503</document_key>
        <order>210</order>
        <sys_class_name>sys_variable_value</sys_class_name>
        <sys_created_by>admin</sys_created_by>
        <sys_created_on>2026-02-20 08:24:46</sys_created_on>
        <sys_id>b5c1132f87073e10375662060cbb3506</sys_id>
        <sys_mod_count>0</sys_mod_count>
        <sys_updated_by>admin</sys_updated_by>
        <sys_updated_on>2026-02-20 08:24:46</sys_updated_on>
        <value/>
        <variable display_value="Not visible">e81ad3535320220002c6435723dc340c</variable>
    </sys_variable_value>
    <sys_variable_value action="DELETE">
        <document>sys_atf_step</document>
        <document_key>bdc1132f87073e10375662060cbb3503</document_key>
        <order>310</order>
        <sys_class_name>sys_variable_value</sys_class_name>
        <sys_created_by>admin</sys_created_by>
        <sys_created_on>2026-02-20 08:24:46</sys_created_on>
        <sys_id>b5c1132f87073e10375662060cbb3507</sys_id>
        <sys_mod_count>0</sys_mod_count>
        <sys_updated_by>admin</sys_updated_by>
        <sys_updated_on>2026-02-20 08:24:46</sys_updated_on>
        <value/>
        <variable display_value="Not read only">e63a97535320220002c6435723dc34b8</variable>
    </sys_variable_value>
    <sys_variable_value action="DELETE">
        <document>sys_atf_step</document>
        <document_key>bdc1132f87073e10375662060cbb3503</document_key>
        <order>100</order>
        <sys_class_name>sys_variable_value</sys_class_name>
        <sys_created_by>admin</sys_created_by>
        <sys_created_on>2026-02-20 08:24:46</sys_created_on>
        <sys_id>b5c1132f87073e10375662060cbb3508</sys_id>
        <sys_mod_count>0</sys_mod_count>
        <sys_updated_by>admin</sys_updated_by>
        <sys_updated_on>2026-02-20 08:24:46</sys_updated_on>
        <value>change_request</value>
        <variable display_value="Table">80f953535320220002c6435723dc340f</variable>
    </sys_variable_value>
    <sys_variable_value action="DELETE">
        <document>sys_atf_step</document>
        <document_key>bdc1132f87073e10375662060cbb3503</document_key>
        <order>50</order>
        <sys_class_name>sys_variable_value</sys_class_name>
        <sys_created_by>admin</sys_created_by>
        <sys_created_on>2026-02-20 08:24:46</sys_created_on>
        <sys_id>bdc1132f87073e10375662060cbb3504</sys_id>
        <sys_mod_count>0</sys_mod_count>
        <sys_updated_by>admin</sys_updated_by>
        <sys_updated_on>2026-02-20 08:24:46</sys_updated_on>
        <value>standard_ui</value>
        <variable display_value="Form UI">b1fefcde73633300b19898b8caf6a7af</variable>
    </sys_variable_value>
    <sys_variable_value action="DELETE">
        <document>sys_atf_step</document>
        <document_key>bdc1132f87073e10375662060cbb3503</document_key>
        <order>300</order>
        <sys_class_name>sys_variable_value</sys_class_name>
        <sys_created_by>admin</sys_created_by>
        <sys_created_on>2026-02-20 08:24:46</sys_created_on>
        <sys_id>bdc1132f87073e10375662060cbb3505</sys_id>
        <sys_mod_count>0</sys_mod_count>
        <sys_updated_by>admin</sys_updated_by>
        <sys_updated_on>2026-02-20 08:24:46</sys_updated_on>
        <value>type,conflict_status,number,conflict_last_run</value>
        <variable display_value="Read only">592a17535320220002c6435723dc34d7</variable>
    </sys_variable_value>
    <sys_variable_value action="DELETE">
        <document>sys_atf_step</document>
        <document_key>bdc1132f87073e10375662060cbb3503</document_key>
        <order>410</order>
        <sys_class_name>sys_variable_value</sys_class_name>
        <sys_created_by>admin</sys_created_by>
        <sys_created_on>2026-02-20 08:24:46</sys_created_on>
        <sys_id>bdc1132f87073e10375662060cbb3506</sys_id>
        <sys_mod_count>0</sys_mod_count>
        <sys_updated_by>admin</sys_updated_by>
        <sys_updated_on>2026-02-20 08:24:46</sys_updated_on>
        <value/>
        <variable display_value="Not mandatory">787a9b535320220002c6435723dc3455</variable>
    </sys_variable_value>
    <sys_variable_value action="DELETE">
        <document>sys_atf_step</document>
        <document_key>bdc1132f87073e10375662060cbb3503</document_key>
        <order>400</order>
        <sys_class_name>sys_variable_value</sys_class_name>
        <sys_created_by>admin</sys_created_by>
        <sys_created_on>2026-02-20 08:24:46</sys_created_on>
        <sys_id>bdc1132f87073e10375662060cbb3507</sys_id>
        <sys_mod_count>0</sys_mod_count>
        <sys_updated_by>admin</sys_updated_by>
        <sys_updated_on>2026-02-20 08:24:46</sys_updated_on>
        <value>description,justification,requested_by,short_description</value>
        <variable display_value="Mandatory">6e5a1b535320220002c6435723dc3498</variable>
    </sys_variable_value>
    <sys_update_version action="INSERT_OR_UPDATE">
        <action>DELETE</action>
        <application display_value="Updater">67d384af87c7b610375662060cbb35be</application>
        <file_path/>
        <instance_id>a2d718a71b2042d08e39415d9c4bcb8f</instance_id>
        <instance_name>summit7systemsdev</instance_name>
        <name>sys_atf_step_bdc1132f87073e10375662060cbb3503</name>
        <payload><![CDATA[<?xml version="1.0" encoding="UTF-8"?><record_update table="sys_atf_step"><sys_atf_step action="INSERT_OR_UPDATE"><active>true</active><callable_outputs/><copied_from/><description>Assert the following:
The following fields are visible: Backout plan, Watch list, Type, Conflict status, Communication Plan, Number, Test plan, CAB delegate, State, Configuration item, Impact, Define Security Impact, Work notes list, Service, Priority, Model, CAB recommendation, Requested by, Actual end date, Work notes, Implementation plan, Planned end date, Short description, Actual start date, Close code, Assignment group, Additional assignee list, Define Proposed Change, Service offering, Close notes, CAB required, Business Justification, Assigned to, Planned start date, Additional comments, Conflict last run, CAB date/time, Risk, Category, Compliance Impact, Operational Impact
The following fields are read only: Type, Conflict status, Number, Conflict last run
The following fields are mandatory: Define Proposed Change, Business Justification, Requested by, Short description
With a failure timeout of 30 Seconds</description><display_name>Field State Validation</display_name><inputs/><mugshots_cache_json/><notes/><order>15</order><step_config display_value="Field State Validation">1dfece935332120028bc29cac2dc3478</step_config><sys_class_name>sys_atf_step</sys_class_name><sys_created_by>admin</sys_created_by><sys_created_on>2026-02-20 08:24:46</sys_created_on><sys_id>bdc1132f87073e10375662060cbb3503</sys_id><sys_mod_count>58</sys_mod_count><sys_name>Field State Validation</sys_name><sys_package display_value="Updater" source="x_g_s7s_updater">67d384af87c7b610375662060cbb35be</sys_package><sys_policy/><sys_scope display_value="Updater">67d384af87c7b610375662060cbb35be</sys_scope><sys_update_name>sys_atf_step_bdc1132f87073e10375662060cbb3503</sys_update_name><sys_updated_by>admin</sys_updated_by><sys_updated_on>2026-02-20 15:23:33</sys_updated_on><table>change_request</table><test display_value="ATF Generated Test - change_request, Jay Simcox, User's default view (Default view)">a0c15feb87073e10375662060cbb357b</test><timeout>1970-01-01 00:00:30</timeout><warning_message/></sys_atf_step><sys_variable_value action="delete_multiple" query="document_key=bdc1132f87073e10375662060cbb3503"/><sys_variable_value action="INSERT_OR_UPDATE"><document>sys_atf_step</document><document_key>bdc1132f87073e10375662060cbb3503</document_key><order>200</order><sys_class_name>sys_variable_value</sys_class_name><sys_created_by>admin</sys_created_by><sys_created_on>2026-02-20 08:24:46</sys_created_on><sys_id>b5c1132f87073e10375662060cbb3505</sys_id><sys_mod_count>0</sys_mod_count><sys_updated_by>admin</sys_updated_by><sys_updated_on>2026-02-20 08:24:46</sys_updated_on><value>backout_plan,watch_list,type,conflict_status,u_communication_plan,number,test_plan,cab_delegate,state,cmdb_ci,impact,u_define_security_impact,work_notes_list,business_service,priority,chg_model,cab_recommendation,requested_by,work_end,work_notes,implementation_plan,end_date,short_description,work_start,close_code,assignment_group,additional_assignee_list,description,service_offering,close_notes,cab_required,justification,assigned_to,start_date,comments,conflict_last_run,cab_date_time,risk,category,u_compliance_impact,risk_impact_analysis</value><variable display_value="Visible">0cd9df135320220002c6435723dc3426</variable></sys_variable_value><sys_variable_value action="INSERT_OR_UPDATE"><document>sys_atf_step</document><document_key>bdc1132f87073e10375662060cbb3503</document_key><order>210</order><sys_class_name>sys_variable_value</sys_class_name><sys_created_by>admin</sys_created_by><sys_created_on>2026-02-20 08:24:46</sys_created_on><sys_id>b5c1132f87073e10375662060cbb3506</sys_id><sys_mod_count>0</sys_mod_count><sys_updated_by>admin</sys_updated_by><sys_updated_on>2026-02-20 08:24:46</sys_updated_on><value/><variable display_value="Not visible">e81ad3535320220002c6435723dc340c</variable></sys_variable_value><sys_variable_value action="INSERT_OR_UPDATE"><document>sys_atf_step</document><document_key>bdc1132f87073e10375662060cbb3503</document_key><order>310</order><sys_class_name>sys_variable_value</sys_class_name><sys_created_by>admin</sys_created_by><sys_created_on>2026-02-20 08:24:46</sys_created_on><sys_id>b5c1132f87073e10375662060cbb3507</sys_id><sys_mod_count>0</sys_mod_count><sys_updated_by>admin</sys_updated_by><sys_updated_on>2026-02-20 08:24:46</sys_updated_on><value/><variable display_value="Not read only">e63a97535320220002c6435723dc34b8</variable></sys_variable_value><sys_variable_value action="INSERT_OR_UPDATE"><document>sys_atf_step</document><document_key>bdc1132f87073e10375662060cbb3503</document_key><order>100</order><sys_class_name>sys_variable_value</sys_class_name><sys_created_by>admin</sys_created_by><sys_created_on>2026-02-20 08:24:46</sys_created_on><sys_id>b5c1132f87073e10375662060cbb3508</sys_id><sys_mod_count>0</sys_mod_count><sys_updated_by>admin</sys_updated_by><sys_updated_on>2026-02-20 08:24:46</sys_updated_on><value>change_request</value><variable display_value="Table">80f953535320220002c6435723dc340f</variable></sys_variable_value><sys_variable_value action="INSERT_OR_UPDATE"><document>sys_atf_step</document><document_key>bdc1132f87073e10375662060cbb3503</document_key><order>50</order><sys_class_name>sys_variable_value</sys_class_name><sys_created_by>admin</sys_created_by><sys_created_on>2026-02-20 08:24:46</sys_created_on><sys_id>bdc1132f87073e10375662060cbb3504</sys_id><sys_mod_count>0</sys_mod_count><sys_updated_by>admin</sys_updated_by><sys_updated_on>2026-02-20 08:24:46</sys_updated_on><value>standard_ui</value><variable display_value="Form UI">b1fefcde73633300b19898b8caf6a7af</variable></sys_variable_value><sys_variable_value action="INSERT_OR_UPDATE"><document>sys_atf_step</document><document_key>bdc1132f87073e10375662060cbb3503</document_key><order>300</order><sys_class_name>sys_variable_value</sys_class_name><sys_created_by>admin</sys_created_by><sys_created_on>2026-02-20 08:24:46</sys_created_on><sys_id>bdc1132f87073e10375662060cbb3505</sys_id><sys_mod_count>0</sys_mod_count><sys_updated_by>admin</sys_updated_by><sys_updated_on>2026-02-20 08:24:46</sys_updated_on><value>type,conflict_status,number,conflict_last_run</value><variable display_value="Read only">592a17535320220002c6435723dc34d7</variable></sys_variable_value><sys_variable_value action="INSERT_OR_UPDATE"><document>sys_atf_step</document><document_key>bdc1132f87073e10375662060cbb3503</document_key><order>410</order><sys_class_name>sys_variable_value</sys_class_name><sys_created_by>admin</sys_created_by><sys_created_on>2026-02-20 08:24:46</sys_created_on><sys_id>bdc1132f87073e10375662060cbb3506</sys_id><sys_mod_count>0</sys_mod_count><sys_updated_by>admin</sys_updated_by><sys_updated_on>2026-02-20 08:24:46</sys_updated_on><value/><variable display_value="Not mandatory">787a9b535320220002c6435723dc3455</variable></sys_variable_value><sys_variable_value action="INSERT_OR_UPDATE"><document>sys_atf_step</document><document_key>bdc1132f87073e10375662060cbb3503</document_key><order>400</order><sys_class_name>sys_variable_value</sys_class_name><sys_created_by>admin</sys_created_by><sys_created_on>2026-02-20 08:24:46</sys_created_on><sys_id>bdc1132f87073e10375662060cbb3507</sys_id><sys_mod_count>0</sys_mod_count><sys_updated_by>admin</sys_updated_by><sys_updated_on>2026-02-20 08:24:46</sys_updated_on><value>description,justification,requested_by,short_description</value><variable display_value="Mandatory">6e5a1b535320220002c6435723dc3498</variable></sys_variable_value></record_update>]]></payload>
        <payload_hash>1976276239</payload_hash>
        <record_name>Field State Validation</record_name>
        <reverted_from/>
        <source>2fd384af87c7b610375662060cbb35c1</source>
        <source_table>sys_update_set</source_table>
        <state>previous</state>
        <sys_created_by>admin</sys_created_by>
        <sys_created_on>2026-02-20 15:23:33</sys_created_on>
        <sys_id>1ca17cbb47433250d5441233e16d43df</sys_id>
        <sys_mod_count>0</sys_mod_count>
        <sys_recorded_at>19c7ba62c8c0000001</sys_recorded_at>
        <sys_updated_by>admin</sys_updated_by>
        <sys_updated_on>2026-02-20 15:23:33</sys_updated_on>
        <type>Test Step</type>
        <update_guid>50a17cbb6143325078f86d06fad12bde</update_guid>
        <update_guid_history>50a17cbb6143325078f86d06fad12bde:1976276239,639178bbe24332502fe9fc31b73d5681:-546094192,bb61bc776a433250124fe8046ca53fb6:1226502673,9b61b877f043325040eddf5fa010a9dc:-1295867758,85613c37a343325017d7fa0e1c1c3aff:476729107,264170b346433250f6e75a23d7b05819:819154473,d22174ffd70332507e67f44ff8626a5c:-1703215958,2211fc7f55033250b646c8470951e09a:69380907,27e074bb83033250ceb575ff9d8e1aa8:1841977772,7ee030bbee0332501b5ba9ee033ba3f9:-680392659,1cd07cf76e03325054c8af152e3c2e60:1092204206,89c0f8b7240332501fe07490f4da3bd9:-1430166225,16b07c7797033250222cc95aeefe1fe9:342430640,65b0b877ba03325011cc5217e2b85073:2115027505,aa5034ffc5cffe106fe4325bb8c571ce:-407342926,edef203b4bcffe101029ba912613e673:-64917560,ffbfe477abcffe10e8d20da0b74c6ee1:1707679305,9eafecf3e5cffe1084b7edc5a73235bd:-814691126,899fa8b3c8cffe10a631050a541cd14a:957905739,0c9fa4b31ecffe1001e9f121b164a41d:-1564464692,d25f68ff258ffe100cae5199bcd45584:208132173,7c3fe87f308ffe10946bed851cdfdabe:1980729038,2f2f287fee8ffe102f6feb4073b4933b:-541641393,6e2f247f1e8ffe10b1db98ed56952d3e:1230955472,e5bea4f7ea8ffe10524f282c57d97673:-1291414959,ccbea0f76a8ffe1032ecd95fa3c9cc55:-948989593,8f4e60b3968ffe1064ab2a73cc1ff567:823607272,303e2c33308ffe10c53df6972e46b847:-1698763159,5b2ee4330b8ffe10c3baa9afe5640d9f:73833706,35c1132fde073e1052c2c45886e4ff17:1846430571</update_guid_history>
    </sys_update_version>
    <sys_metadata_delete action="INSERT_OR_UPDATE">
        <sys_audit_delete/>
        <sys_class_name>sys_metadata_delete</sys_class_name>
        <sys_created_by>admin</sys_created_by>
        <sys_created_on>2026-02-20 15:23:55</sys_created_on>
        <sys_db_object display_value="" name="sys_atf_step">sys_atf_step</sys_db_object>
        <sys_id>24b6e89e67454ec79f00c175fff0dca9</sys_id>
        <sys_metadata>bdc1132f87073e10375662060cbb3503</sys_metadata>
        <sys_mod_count>0</sys_mod_count>
        <sys_name>Field State Validation</sys_name>
        <sys_package display_value="Updater" source="x_g_s7s_updater">67d384af87c7b610375662060cbb35be</sys_package>
        <sys_parent/>
        <sys_policy/>
        <sys_scope display_value="Updater">67d384af87c7b610375662060cbb35be</sys_scope>
        <sys_scope_delete display_value="">2e01286e573e42da91d72c8407412df1</sys_scope_delete>
        <sys_update_name>sys_atf_step_bdc1132f87073e10375662060cbb3503</sys_update_name>
        <sys_update_version display_value="sys_atf_step_bdc1132f87073e10375662060cbb3503">1ca17cbb47433250d5441233e16d43df</sys_update_version>
        <sys_updated_by>admin</sys_updated_by>
        <sys_updated_on>2026-02-20 15:23:55</sys_updated_on>
    </sys_metadata_delete>
</record_update>
