<?xml version="1.0" encoding="UTF-8"?><record_update table="sys_atf_step">
    <sys_atf_step action="DELETE">
        <active>true</active>
        <callable_outputs/>
        <copied_from/>
        <description>Validate that the form matches the following condition:
Score = 4.67
and Project manager = Narcesse Louis
and State = Pending
and Phase = Initiating
and Priority = 4 - Low
and Derive assignee list from resource plan = false
and Value Score = 5
and Risk Score = 4
and Status = Green
and Project Name starts with TM/Akita Innovations - Offboarding
and Assignment group = grp-Managed Services
and Calculation = Automatic
and Execution type = Waterfall
and Department = Program Management Office (PMO)
and Size Score = 5
and Percent complete = 0
and Schedule = Project Management Schedule
and Beta = false
With a failure timeout of 30 Seconds</description>
        <display_name>Field Values Validation</display_name>
        <inputs/>
        <mugshots_cache_json/>
        <notes/>
        <order>58</order>
        <step_config display_value="Field Values Validation">1b97cd31872022008182c9ded0e3ece5</step_config>
        <sys_class_name>sys_atf_step</sys_class_name>
        <sys_created_by>admin</sys_created_by>
        <sys_created_on>2026-02-20 04:32:51</sys_created_on>
        <sys_id>54bc966f478bfa10d5441233e16d4352</sys_id>
        <sys_mod_count>0</sys_mod_count>
        <sys_name>Field Values Validation</sys_name>
        <sys_package display_value="Updater" source="x_g_s7s_updater">67d384af87c7b610375662060cbb35be</sys_package>
        <sys_policy/>
        <sys_scope display_value="Updater">67d384af87c7b610375662060cbb35be</sys_scope>
        <sys_update_name>sys_atf_step_54bc966f478bfa10d5441233e16d4352</sys_update_name>
        <sys_updated_by>admin</sys_updated_by>
        <sys_updated_on>2026-02-20 04:32:51</sys_updated_on>
        <table>customer_project</table>
        <test display_value="ATF Generated Test - customer_project, Narcesse Louis, User's default view (Default view)">8facd62f478bfa10d5441233e16d43e6</test>
        <timeout>1970-01-01 00:00:30</timeout>
        <warning_message/>
    </sys_atf_step>
    <sys_variable_value action="DELETE" query="document_key=54bc966f478bfa10d5441233e16d4352"/>
    <sys_variable_value action="DELETE">
        <document>sys_atf_step</document>
        <document_key>54bc966f478bfa10d5441233e16d4352</document_key>
        <order>100</order>
        <sys_class_name>sys_variable_value</sys_class_name>
        <sys_created_by>admin</sys_created_by>
        <sys_created_on>2026-02-20 04:32:51</sys_created_on>
        <sys_id>10bc966f478bfa10d5441233e16d4357</sys_id>
        <sys_mod_count>0</sys_mod_count>
        <sys_updated_by>admin</sys_updated_by>
        <sys_updated_on>2026-02-20 04:32:51</sys_updated_on>
        <value>customer_project</value>
        <variable display_value="Table">a0e13cc35320220002c6435723dc3467</variable>
    </sys_variable_value>
    <sys_variable_value action="DELETE">
        <document>sys_atf_step</document>
        <document_key>54bc966f478bfa10d5441233e16d4352</document_key>
        <order>50</order>
        <sys_class_name>sys_variable_value</sys_class_name>
        <sys_created_by>admin</sys_created_by>
        <sys_created_on>2026-02-20 04:32:51</sys_created_on>
        <sys_id>94bc966f478bfa10d5441233e16d4356</sys_id>
        <sys_mod_count>0</sys_mod_count>
        <sys_updated_by>admin</sys_updated_by>
        <sys_updated_on>2026-02-20 04:32:51</sys_updated_on>
        <value>standard_ui</value>
        <variable display_value="Form UI">c83b5337e7633300e12127d8d2f6a98b</variable>
    </sys_variable_value>
    <sys_variable_value action="DELETE">
        <document>sys_atf_step</document>
        <document_key>54bc966f478bfa10d5441233e16d4352</document_key>
        <order>200</order>
        <sys_class_name>sys_variable_value</sys_class_name>
        <sys_created_by>admin</sys_created_by>
        <sys_created_on>2026-02-20 04:32:51</sys_created_on>
        <sys_id>d8bc966f478bfa10d5441233e16d4356</sys_id>
        <sys_mod_count>0</sys_mod_count>
        <sys_updated_by>admin</sys_updated_by>
        <sys_updated_on>2026-02-20 04:32:51</sys_updated_on>
        <value>score=4.67^project_manager=f0de806e97564a1047d9f64ef053afeb^state=-5^phase=initiating^priority=4^resources_from_resource_plan=false^score_value=5^score_risk=4^status=green^short_descriptionSTARTSWITHTM/Akita Innovations - Offboarding^assignment_group=6aee486e97564a1047d9f64ef053af61^calculation_type=automatic^execution_type=waterfall^department=9a8e963f979c1a502a4cbb0de053af27^score_size=5^percent_complete=0^schedule=7aa3e10c8f70010040f82ab2f0f9234d^u_beta=false</value>
        <variable display_value="Conditions">4aa838f25320220002c6435723dc34e1</variable>
    </sys_variable_value>
    <sys_element_mapping action="DELETE" query="table=var__m_atf_input_variable_1b97cd31872022008182c9ded0e3ece5^id=54bc966f478bfa10d5441233e16d4352"/>
    <sys_update_version action="INSERT_OR_UPDATE">
        <action>DELETE</action>
        <application display_value="Updater">67d384af87c7b610375662060cbb35be</application>
        <file_path/>
        <instance_id>a2d718a71b2042d08e39415d9c4bcb8f</instance_id>
        <instance_name>summit7systemsdev</instance_name>
        <name>sys_atf_step_54bc966f478bfa10d5441233e16d4352</name>
        <payload><![CDATA[<?xml version="1.0" encoding="UTF-8"?><record_update table="sys_atf_step"><sys_atf_step action="INSERT_OR_UPDATE"><active>true</active><callable_outputs/><copied_from/><description>Validate that the form matches the following condition:
Score = 4.67
and Project manager = Narcesse Louis
and State = Pending
and Phase = Initiating
and Priority = 4 - Low
and Derive assignee list from resource plan = false
and Value Score = 5
and Risk Score = 4
and Status = Green
and Project Name starts with TM/Akita Innovations - Offboarding
and Assignment group = grp-Managed Services
and Calculation = Automatic
and Execution type = Waterfall
and Department = Program Management Office (PMO)
and Size Score = 5
and Percent complete = 0
and Schedule = Project Management Schedule
and Beta = false
With a failure timeout of 30 Seconds</description><display_name>Field Values Validation</display_name><inputs/><mugshots_cache_json/><notes/><order>58</order><step_config display_value="Field Values Validation">1b97cd31872022008182c9ded0e3ece5</step_config><sys_class_name>sys_atf_step</sys_class_name><sys_created_by>admin</sys_created_by><sys_created_on>2026-02-20 04:32:51</sys_created_on><sys_id>54bc966f478bfa10d5441233e16d4352</sys_id><sys_mod_count>0</sys_mod_count><sys_name>Field Values Validation</sys_name><sys_package display_value="Updater" source="x_g_s7s_updater">67d384af87c7b610375662060cbb35be</sys_package><sys_policy/><sys_scope display_value="Updater">67d384af87c7b610375662060cbb35be</sys_scope><sys_update_name>sys_atf_step_54bc966f478bfa10d5441233e16d4352</sys_update_name><sys_updated_by>admin</sys_updated_by><sys_updated_on>2026-02-20 04:32:51</sys_updated_on><table>customer_project</table><test display_value="ATF Generated Test - customer_project, Narcesse Louis, User's default view (Default view)">8facd62f478bfa10d5441233e16d43e6</test><timeout>1970-01-01 00:00:30</timeout><warning_message/></sys_atf_step><sys_variable_value action="delete_multiple" query="document_key=54bc966f478bfa10d5441233e16d4352"/><sys_variable_value action="INSERT_OR_UPDATE"><document>sys_atf_step</document><document_key>54bc966f478bfa10d5441233e16d4352</document_key><order>100</order><sys_class_name>sys_variable_value</sys_class_name><sys_created_by>admin</sys_created_by><sys_created_on>2026-02-20 04:32:51</sys_created_on><sys_id>10bc966f478bfa10d5441233e16d4357</sys_id><sys_mod_count>0</sys_mod_count><sys_updated_by>admin</sys_updated_by><sys_updated_on>2026-02-20 04:32:51</sys_updated_on><value>customer_project</value><variable display_value="Table">a0e13cc35320220002c6435723dc3467</variable></sys_variable_value><sys_variable_value action="INSERT_OR_UPDATE"><document>sys_atf_step</document><document_key>54bc966f478bfa10d5441233e16d4352</document_key><order>50</order><sys_class_name>sys_variable_value</sys_class_name><sys_created_by>admin</sys_created_by><sys_created_on>2026-02-20 04:32:51</sys_created_on><sys_id>94bc966f478bfa10d5441233e16d4356</sys_id><sys_mod_count>0</sys_mod_count><sys_updated_by>admin</sys_updated_by><sys_updated_on>2026-02-20 04:32:51</sys_updated_on><value>standard_ui</value><variable display_value="Form UI">c83b5337e7633300e12127d8d2f6a98b</variable></sys_variable_value><sys_variable_value action="INSERT_OR_UPDATE"><document>sys_atf_step</document><document_key>54bc966f478bfa10d5441233e16d4352</document_key><order>200</order><sys_class_name>sys_variable_value</sys_class_name><sys_created_by>admin</sys_created_by><sys_created_on>2026-02-20 04:32:51</sys_created_on><sys_id>d8bc966f478bfa10d5441233e16d4356</sys_id><sys_mod_count>0</sys_mod_count><sys_updated_by>admin</sys_updated_by><sys_updated_on>2026-02-20 04:32:51</sys_updated_on><value>score=4.67^project_manager=f0de806e97564a1047d9f64ef053afeb^state=-5^phase=initiating^priority=4^resources_from_resource_plan=false^score_value=5^score_risk=4^status=green^short_descriptionSTARTSWITHTM/Akita Innovations - Offboarding^assignment_group=6aee486e97564a1047d9f64ef053af61^calculation_type=automatic^execution_type=waterfall^department=9a8e963f979c1a502a4cbb0de053af27^score_size=5^percent_complete=0^schedule=7aa3e10c8f70010040f82ab2f0f9234d^u_beta=false</value><variable display_value="Conditions">4aa838f25320220002c6435723dc34e1</variable></sys_variable_value><sys_element_mapping action="delete_multiple" query="table=var__m_atf_input_variable_1b97cd31872022008182c9ded0e3ece5^id=54bc966f478bfa10d5441233e16d4352"/></record_update>]]></payload>
        <payload_hash>-636094631</payload_hash>
        <record_name>Field Values Validation</record_name>
        <reverted_from/>
        <source>2fd384af87c7b610375662060cbb35c1</source>
        <source_table>sys_update_set</source_table>
        <state>previous</state>
        <sys_created_by>admin</sys_created_by>
        <sys_created_on>2026-02-20 04:32:51</sys_created_on>
        <sys_id>1cbc966f478bfa10d5441233e16d43ca</sys_id>
        <sys_mod_count>0</sys_mod_count>
        <sys_recorded_at>19c79526e320000001</sys_recorded_at>
        <sys_updated_by>admin</sys_updated_by>
        <sys_updated_on>2026-02-20 04:32:51</sys_updated_on>
        <type>Test Step</type>
        <update_guid>d4bc966f078bfa107279709433ca3e59</update_guid>
        <update_guid_history>d4bc966f078bfa107279709433ca3e59:-636094631</update_guid_history>
    </sys_update_version>
    <sys_metadata_delete action="INSERT_OR_UPDATE">
        <sys_audit_delete/>
        <sys_class_name>sys_metadata_delete</sys_class_name>
        <sys_created_by>admin</sys_created_by>
        <sys_created_on>2026-02-20 04:59:07</sys_created_on>
        <sys_db_object display_value="" name="sys_atf_step">sys_atf_step</sys_db_object>
        <sys_id>6463666660c44c97bed053c4cbc1f739</sys_id>
        <sys_metadata>54bc966f478bfa10d5441233e16d4352</sys_metadata>
        <sys_mod_count>0</sys_mod_count>
        <sys_name>Field Values Validation</sys_name>
        <sys_package display_value="Updater" source="x_g_s7s_updater">67d384af87c7b610375662060cbb35be</sys_package>
        <sys_parent/>
        <sys_policy/>
        <sys_scope display_value="Updater">67d384af87c7b610375662060cbb35be</sys_scope>
        <sys_scope_delete display_value="">2e01286e573e42da91d72c8407412df1</sys_scope_delete>
        <sys_update_name>sys_atf_step_54bc966f478bfa10d5441233e16d4352</sys_update_name>
        <sys_update_version display_value="sys_atf_step_54bc966f478bfa10d5441233e16d4352">1cbc966f478bfa10d5441233e16d43ca</sys_update_version>
        <sys_updated_by>admin</sys_updated_by>
        <sys_updated_on>2026-02-20 04:59:07</sys_updated_on>
    </sys_metadata_delete>
</record_update>
